cognition_core/__init__.py
cognition_core/agent.py
cognition_core/api.py
cognition_core/config.py
cognition_core/crew.py
cognition_core/flow.py
cognition_core/llm.py
cognition_core/logger.py
cognition_core/task.py
cognition_core/flows/README.md
cognition_core/flows/cloud_resource_flow.py
cognition_core/flows/code_review_flow.py
cognition_core/flows/examples/cloud_resource_example.py
cognition_core/flows/examples/code_review_example.py
cognition_core/memory/entity.py
cognition_core/memory/long_term.py
cognition_core/memory/mem_svc.py
cognition_core/memory/short_term.py
cognition_core/memory/storage.py
cognition_core/tools/__init__.py
cognition_core/tools/custom_tool.py
cognition_core/tools/tool_svc.py
cognition_core-0.6.0.dist-info/METADATA
cognition_core-0.6.0.dist-info/WHEEL
cognition_core-0.6.0.dist-info/RECORD
