Metadata-Version: 2.4
Name: cognition-core
Version: 0.6.0
Summary: Core integration package for building AI agents with CrewAI, providing configuration management, memory systems, and tool integration
Project-URL: Homepage, https://github.com/nestorcolt/cognition-core
Project-URL: Repository, https://github.com/nestorcolt/cognition-core
Project-URL: Documentation, https://github.com/nestorcolt/cognition-core#readme
Author-email: Nestor Colt <nestor.colt@gmail.com>
License: MIT
Classifier: Development Status :: 3 - Alpha
Classifier: Intended Audience :: Developers
Classifier: License :: OSI Approved :: MIT License
Classifier: Programming Language :: Python :: 3
Classifier: Programming Language :: Python :: 3.10
Classifier: Programming Language :: Python :: 3.11
Classifier: Programming Language :: Python :: 3.12
Classifier: Topic :: Scientific/Engineering :: Artificial Intelligence
Classifier: Topic :: Software Development :: Libraries :: Python Modules
Requires-Python: <3.13,>=3.10
Requires-Dist: chromadb>=0.4.0
Requires-Dist: colorama>=0.4.6
Requires-Dist: crewai
Requires-Dist: crewai[tools]
Requires-Dist: langchain-community>=0.0.27
Requires-Dist: portkey-ai
Requires-Dist: psycopg2-binary>=2.9.9
Requires-Dist: pydantic>=2.0.0
Requires-Dist: pyyaml>=6.0.1
Requires-Dist: watchdog>=3.0.0
